[
  {
    "id": "yurihama-childcare-001",
    "name": "児童手当",
    "category": "childcare",
    "cityCode": "31302",
    "cityName": "湯梨浜町",
    "prefecture": "鳥取県",
    "summary": "18歳年度末までの児童を養育する保護者に支給。所得制限なし。",
    "target": "18歳年度末までの児童を養育する保護者",
    "amount": "月額10,000〜30,000円（年齢・子の数による）",
    "maxAmount": 30000,
    "deadline": "出生・転入日から15日以内に申請",
    "officialUrl": "https://www.yurihama.jp/soshiki/3/1553.html",
    "status": "active",
    "lastUpdated": "2026-03-27"
  },
  {
    "id": "yurihama-birth-001",
    "name": "出産・子育て応援給付金",
    "category": "birth",
    "cityCode": "31302",
    "cityName": "湯梨浜町",
    "prefecture": "鳥取県",
    "summary": "妊娠届出後に5万円、出生届出後に5万円、計10万円を支給。",
    "target": "妊娠届出・出生届出をした保護者",
    "amount": "計10万円（妊娠届出後5万円＋出生届出後5万円）",
    "maxAmount": 100000,
    "deadline": "通年",
    "officialUrl": "https://www.yurihama.jp/soshiki/3/1553.html",
    "status": "active",
    "lastUpdated": "2026-03-27"
  },
  {
    "id": "yurihama-medical-001",
    "name": "子ども医療費助成",
    "category": "medical",
    "cityCode": "31302",
    "cityName": "湯梨浜町",
    "prefecture": "鳥取県",
    "summary": "18歳年度末までの児童の医療費自己負担分を助成。",
    "target": "18歳年度末までの児童（湯梨浜町在住・健康保険加入）",
    "amount": "保険診療の自己負担金を助成",
    "maxAmount": 0,
    "deadline": "通年",
    "officialUrl": "https://www.yurihama.jp/soshiki/3/1553.html",
    "status": "active",
    "lastUpdated": "2026-03-27"
  },
  {
    "id": "yurihama-moving-001",
    "name": "若者夫婦・子育て世代住宅支援事業補助金",
    "category": "moving",
    "cityCode": "31302",
    "cityName": "湯梨浜町",
    "prefecture": "鳥取県",
    "summary": "若者夫婦や子育て世代の住宅取得・リフォームを支援。",
    "target": "若者夫婦（夫婦ともに40歳未満）または子育て世代",
    "amount": "住宅取得・リフォーム費用の一部を補助",
    "maxAmount": 500000,
    "deadline": "予算がなくなり次第終了",
    "officialUrl": "https://www.yurihama.jp/soshiki/3/1553.html",
    "status": "active",
    "lastUpdated": "2026-03-27"
  },
  {
    "id": "yurihama-safety-001",
    "name": "老朽危険空き家等除却支援事業",
    "category": "safety",
    "cityCode": "31302",
    "cityName": "湯梨浜町",
    "prefecture": "鳥取県",
    "summary": "老朽化した危険な空き家の除却費用の一部を補助。",
    "target": "老朽危険空き家の所有者",
    "amount": "除却費用の一部を補助（上限50万円）",
    "maxAmount": 500000,
    "deadline": "予算がなくなり次第終了",
    "officialUrl": "https://www.yurihama.jp/soshiki/3/1553.html",
    "status": "active",
    "lastUpdated": "2026-03-27"
  },
  {
    "id": "yurihama-safety-002",
    "name": "ブロック塀撤去・改修支援事業",
    "category": "safety",
    "cityCode": "31302",
    "cityName": "湯梨浜町",
    "prefecture": "鳥取県",
    "summary": "危険なブロック塀の撤去・改修費用の一部を補助。",
    "target": "危険なブロック塀の所有者",
    "amount": "撤去・改修費用の一部を補助",
    "maxAmount": 200000,
    "deadline": "予算がなくなり次第終了",
    "officialUrl": "https://www.yurihama.jp/soshiki/3/1553.html",
    "status": "active",
    "lastUpdated": "2026-03-27"
  },
  {
    "id": "yurihama-childcare-002",
    "name": "児童扶養手当",
    "category": "childcare",
    "cityCode": "31302",
    "cityName": "湯梨浜町",
    "prefecture": "鳥取県",
    "summary": "ひとり親家庭等の児童の福祉増進のため手当を支給。",
    "target": "ひとり親家庭等で18歳年度末までの児童を養育する方",
    "amount": "月額最大44,140円（児童1人の場合）",
    "maxAmount": 44140,
    "deadline": "通年",
    "officialUrl": "https://www.yurihama.jp/soshiki/3/1553.html",
    "status": "active",
    "lastUpdated": "2026-03-27"
  },
  {
    "id": "yurihama-solar-001",
    "name": "省エネ設備導入補助金",
    "category": "solar",
    "cityCode": "31302",
    "cityName": "湯梨浜町",
    "prefecture": "鳥取県",
    "summary": "省エネ効果の高い設備等の導入経費の一部を補助。中小企業者等のエネルギーコスト削減を支援。",
    "target": "町内の中小企業者等",
    "amount": "上限100万円",
    "maxAmount": 1000000,
    "deadline": "2026年11月30日まで",
    "officialUrl": "https://www.yurihama.jp/soshiki/3/1553.html",
    "status": "active",
    "lastUpdated": "2026-03-27"
  }
]
